cpykg/__init__.py
cpykg/module.py
cpykg/utils.py
cpykg/data/AISecKG.csv
cpykg/data/MetaQA_KG.csv
cpykg/data/R25KG_rare.csv
cpykg/data/SDKG_Dis11.csv
cpykg-0.0.10.dist-info/LICENSE
cpykg-0.0.10.dist-info/METADATA
cpykg-0.0.10.dist-info/WHEEL
cpykg-0.0.10.dist-info/top_level.txt
cpykg-0.0.10.dist-info/RECORD
