Metadata-Version: 2.1
Name: cpykg
Version: 0.0.10
Summary: Knowledge Graph Repository
Author-email: Cameron Pykiet <pykietcj11@gmail.com>
Classifier: Programming Language :: Python :: 3
Classifier: License :: OSI Approved :: MIT License
Classifier: Operating System :: OS Independent
Requires-Python: >=3.8
License-File: LICENSE
Requires-Dist: py2neo
Requires-Dist: yfiles-jupyter-graphs-for-neo4j
Requires-Dist: neo4j
